<?xml version = "1.0" encoding = "UTF-8"?>
<frameworks>
    <framework>
        <nombre>.NET</nombre>
        <lenguaje>C# y otros</lenguaje>
        <fundador>Microsoft</fundador>
    </framework>
    
    <framework>
        <nombre>Zend</nombre>
        <lenguaje>PHP</lenguaje>
        <fundador>Zend</fundador>
    </framework>
    
    <framework>
        <nombre>Spring</nombre>
        <lenguaje>Java</lenguaje>
        <fundador>Pivotal</fundador>
    </framework>
    
    <framework>
        <nombre>Laravel</nombre>
        <lenguaje>PHP</lenguaje>
        <fundador>Taylor Otwell</fundador>
    </framework>
</frameworks>
